nonebot_plugin_theworld/__init__.py
nonebot_plugin_theworld/resources/图片1.png
nonebot_plugin_theworld/resources/图片2.png
nonebot_plugin_theworld/resources/图片3.png
nonebot_plugin_theworld/resources/图片4.png
nonebot_plugin_theworld/resources/图片5.png
nonebot_plugin_theworld/resources/图片6.png
nonebot_plugin_theworld/resources/图片7.png
nonebot_plugin_theworld/resources/图片8.png
nonebot_plugin_theworld/resources/图片9.png
nonebot_plugin_theworld/resources/声音1.mp3
nonebot_plugin_theworld/resources/声音10.mp3
nonebot_plugin_theworld/resources/声音11.mp3
nonebot_plugin_theworld/resources/声音12.mp3
nonebot_plugin_theworld/resources/声音2.mp3
nonebot_plugin_theworld/resources/声音3.mp3
nonebot_plugin_theworld/resources/声音4.mp3
nonebot_plugin_theworld/resources/声音5.mp3
nonebot_plugin_theworld/resources/声音6.mp3
nonebot_plugin_theworld/resources/声音7.mp3
nonebot_plugin_theworld/resources/声音8.mp3
nonebot_plugin_theworld/resources/声音9.mp3
nonebot_plugin_theworld-0.1.1.dist-info/WHEEL
nonebot_plugin_theworld-0.1.1.dist-info/METADATA
nonebot_plugin_theworld-0.1.1.dist-info/licenses/LICENSE
nonebot_plugin_theworld-0.1.1.dist-info/RECORD
