Metadata-Version: 2.1
Name: nonebot-plugin-theworld
Version: 0.1.1
Summary: 「ザ・ワールド」ッ！ 時よ止まれ！
License: MIT
Author-email: Akirami <Akiramiaya@outlook.com>
Requires-Python: >=3.8
Requires-Dist: nonebot-adapter-onebot>=2.2.3
Requires-Dist: nonebot2>=2.0.1
Project-URL: Homepage, https://github.com/A-kirami/nonebot-plugin-theworld
Project-URL: Repository, https://github.com/A-kirami/nonebot-plugin-theworld
